autosar_calltree/__init__.py
autosar_calltree/version.py
autosar_calltree/analyzers/__init__.py
autosar_calltree/analyzers/call_tree_builder.py
autosar_calltree/cli/__init__.py
autosar_calltree/cli/main.py
autosar_calltree/config/__init__.py
autosar_calltree/config/module_config.py
autosar_calltree/database/__init__.py
autosar_calltree/database/function_database.py
autosar_calltree/database/models.py
autosar_calltree/generators/__init__.py
autosar_calltree/generators/mermaid_generator.py
autosar_calltree/parsers/__init__.py
autosar_calltree/parsers/autosar_parser.py
autosar_calltree/parsers/c_parser.py
autosar_calltree-0.3.3.dist-info/licenses/LICENSE
autosar_calltree-0.3.3.dist-info/METADATA
autosar_calltree-0.3.3.dist-info/WHEEL
autosar_calltree-0.3.3.dist-info/entry_points.txt
autosar_calltree-0.3.3.dist-info/top_level.txt
autosar_calltree-0.3.3.dist-info/RECORD
