Metadata-Version: 2.4
Name: autosar-calltree
Version: 0.3.3
Summary: A Python tool to analyze C/AUTOSAR codebases and generate function call trees with Mermaid and XMI output
Author-email: melodypapa <melodypapa@outlook.com>
Maintainer-email: melodypapa <melodypapa@outlook.com>
License: MIT
Project-URL: Homepage, https://github.com/melodypapa/autosar-calltree
Project-URL: Documentation, https://autosar-calltree.readthedocs.io
Project-URL: Repository, https://github.com/melodypapa/autosar-calltree
Project-URL: Bug Tracker, https://github.com/melodypapa/autosar-calltree/issues
Keywords: autosar,c,call-tree,static-analysis,code-analysis,mermaid,xmi,uml,embedded,automotive
Classifier: Development Status :: 3 - Alpha
Classifier: Intended Audience :: Developers
Classifier: Topic :: Software Development :: Code Generators
Classifier: Topic :: Software Development :: Documentation
Classifier: License :: OSI Approved :: MIT License
Classifier: Programming Language :: Python :: 3
Classifier: Programming Language :: Python :: 3.8
Classifier: Programming Language :: Python :: 3.9
Classifier: Programming Language :: Python :: 3.10
Classifier: Programming Language :: Python :: 3.11
Classifier: Programming Language :: Python :: 3.12
Classifier: Operating System :: OS Independent
Requires-Python: >=3.8
License-File: LICENSE
Requires-Dist: click>=8.0.0
Requires-Dist: rich>=10.0.0
Requires-Dist: pydantic>=2.0.0
Requires-Dist: jinja2>=3.0.0
Requires-Dist: pyyaml>=6.0
Provides-Extra: dev
Requires-Dist: pytest>=7.0.0; extra == "dev"
Requires-Dist: pytest-cov>=3.0.0; extra == "dev"
Requires-Dist: black==24.8.0; extra == "dev"
Requires-Dist: ruff>=0.0.0; extra == "dev"
Requires-Dist: flake8>=4.0.0; extra == "dev"
Requires-Dist: mypy>=0.950; extra == "dev"
Requires-Dist: isort>=5.10.0; extra == "dev"
Provides-Extra: docs
Requires-Dist: sphinx>=4.0.0; extra == "docs"
Requires-Dist: sphinx-rtd-theme>=1.0.0; extra == "docs"
Requires-Dist: sphinx-click>=3.0.0; extra == "docs"
Dynamic: license-file
